flask_admin.py-0.1.3.dist-info/RECORD
flask_admin.py-0.1.3.dist-info/top_level.txt
flask_admin.py-0.1.3.dist-info/METADATA
flask_admin.py-0.1.3.dist-info/metadata.json
flask_admin.py-0.1.3.dist-info/WHEEL
flask_admin.py-0.1.3.dist-info/entry_points.txt
flask_admin.py-0.1.3.dist-info/DESCRIPTION.rst
flask_admin.py-0.1.3.dist-info/zip-safe
flask/admin.py
flask/__init__.py
