Metadata-Version: 2.0
Name: flask-admin.py
Version: 0.1.3
Summary: copy from djang-admin.py
Home-page: https://github.com/konglx90/flask-admin.py
Author: konglx90
Author-email: konglx90@gmail.com
License: MIT
Keywords: python flask flask-admin.py
Platform: UNKNOWN
